odoo10_addon_connector_lengow_naturedecouvertes-10.0.1.0.0.99.dev5-py2.7-nspkg.pth
odoo/addons/connector_lengow_naturedecouvertes/README.rst
odoo/addons/connector_lengow_naturedecouvertes/__init__.py
odoo/addons/connector_lengow_naturedecouvertes/__manifest__.py
odoo/addons/connector_lengow_naturedecouvertes/data/lengow_data.xml
odoo/addons/connector_lengow_naturedecouvertes/i18n/connector_lengow_naturedecouvertes.pot
odoo/addons/connector_lengow_naturedecouvertes/models/__init__.py
odoo/addons/connector_lengow_naturedecouvertes/models/configurator.py
odoo/addons/connector_lengow_naturedecouvertes/static/description/icon.png
odoo/addons/connector_lengow_naturedecouvertes/tests/__init__.py
odoo/addons/connector_lengow_naturedecouvertes/tests/test_lengow_stock.py
odoo10_addon_connector_lengow_naturedecouvertes-10.0.1.0.0.99.dev5.dist-info/METADATA
odoo10_addon_connector_lengow_naturedecouvertes-10.0.1.0.0.99.dev5.dist-info/RECORD
odoo10_addon_connector_lengow_naturedecouvertes-10.0.1.0.0.99.dev5.dist-info/WHEEL
odoo10_addon_connector_lengow_naturedecouvertes-10.0.1.0.0.99.dev5.dist-info/namespace_packages.txt
odoo10_addon_connector_lengow_naturedecouvertes-10.0.1.0.0.99.dev5.dist-info/top_level.txt
